chartis/__about__.py
chartis/__init__.py
chartis/composer/__init__.py
chartis/composer/operators/__init__.py
chartis/composer/operators/bashoperator.cwl
chartis/composer/operators/dummyoperator.cwl
chartis/cwl/__init__.py
chartis-0.0.2.dist-info/METADATA
chartis-0.0.2.dist-info/WHEEL
chartis-0.0.2.dist-info/entry_points.txt
chartis-0.0.2.dist-info/top_level.txt
chartis-0.0.2.dist-info/RECORD
