Metadata-Version: 2.1
Name: chartis
Version: 0.0.2
Summary: Useful things for Airflow.
Home-page: http://github.com/trejas/chartis
Author: Trey Hatch
Author-email: trey@newmathdata.com
License: MIT
Project-URL: Source, https://github.com/trejas/chartis
Platform: UNKNOWN
Classifier: Development Status :: 5 - Production/Stable
Classifier: Intended Audience :: Developers
Classifier: Natural Language :: English
Classifier: License :: OSI Approved :: Apache Software License
Classifier: Programming Language :: Python
Classifier: Programming Language :: Python :: 3.6
Classifier: Programming Language :: Python :: 3.7
Classifier: Programming Language :: Python :: 3.8
Classifier: Programming Language :: Python :: Implementation :: CPython
Classifier: Programming Language :: Python :: Implementation :: PyPy
Requires-Python: >=3.7
